{
  "employee": [
    {
      "name": "Rutuja Patil",
      "profile": "../assets/profile2.png",
      "gender": "Female",
      "department": [
        "SALES",
        "FINANCE"
      ],
      "salary": "30000",
      "startdate": "16/Sept/2020",
      "note": "javaScript",
      "id": 1
    },
    {
      "name": "Shubhangi Patil",
      "profile": "../assets/profile2.png",
      "gender": "Female",
      "department": "SALES",
      "salary": "30000",
      "startdate": "17/Oct/2021",
      "note": "java",
      "id": 2
    },
    {
      "name": "Shiv",
      "profile": "../assets/profile1.png",
      "gender": "Male",
      "department": [
        "HR",
        "SALES"
      ],
      "salary": "40000",
      "startdate": "15/Oct/2018",
      "note": "mdjbsdhnk",
      "id": 4
    }
  ]
}